QuICT_ml/__init__.py
QuICT_ml/ansatz_library/QNN_layer.py
QuICT_ml/ansatz_library/__init__.py
QuICT_ml/ansatz_library/thouless_ansatz.py
QuICT_ml/model/__init__.py
QuICT_ml/model/QNN/__init__.py
QuICT_ml/model/QNN/mnist_classifier_net.py
QuICT_ml/model/VQA/__init__.py
QuICT_ml/model/VQA/qaoa_net.py
QuICT_ml/model/VQA/vqe_net.py
QuICT_ml/model/VQE/__init__.py
QuICT_ml/model/VQE/hartree_fock_net.py
QuICT_ml/model/VQE/operators/__init__.py
QuICT_ml/model/VQE/operators/encoder.py
QuICT_ml/model/VQE/operators/fermion_operator.py
QuICT_ml/model/VQE/operators/polynomial_operator.py
QuICT_ml/model/VQE/operators/qubit_operator.py
QuICT_ml/rl_mapping/__init__.py
QuICT_ml/rl_mapping/data_def.py
QuICT_ml/rl_mapping/rl_mapping.py
QuICT_ml/rl_mapping/net/__init__.py
QuICT_ml/rl_mapping/net/nn_mapping.py
QuICT_ml/rl_mapping/net/rl_agent.py
QuICT_ml/rl_mapping/train/__init__.py
QuICT_ml/rl_mapping/train/actor.py
QuICT_ml/rl_mapping/train/learner.py
QuICT_ml/rl_mapping/train/train_rl.py
QuICT_ml/rl_mapping/utility/__init__.py
QuICT_ml/rl_mapping/utility/cmp_data.py
QuICT_ml/rl_mapping/utility/v_data.py
QuICT_ml/tools/__init__.py
QuICT_ml/tools/exception/__init__.py
QuICT_ml/tools/exception/qml_algorithm_exception.py
QuICT_ml/tools/exception/qml_framework_exception.py
QuICT_ml/trained_models/QNN_MNIST.ckpt
QuICT_ml/utils/__init__.py
QuICT_ml/utils/ansatz.py
QuICT_ml/utils/encoding.py
QuICT_ml/utils/gate_tensor.py
QuICT_ml/utils/gpu_gate_simulator.py
QuICT_ml/utils/hamiltonian.py
QuICT_ml/utils/ml_utils.py
quict_ml-0.9.6.data/data/QuICT_ml/trained_models/QNN_MNIST.ckpt
quict_ml-0.9.6.dist-info/METADATA
quict_ml-0.9.6.dist-info/WHEEL
quict_ml-0.9.6.dist-info/top_level.txt
quict_ml-0.9.6.dist-info/RECORD
