Metadata-Version: 2.1
Name: quict-ml
Version: 0.9.6
Summary: Quantum Machine Learning Framework for QuICT.
Home-page: https://edu.gitee.com/quictucas/repos/quictucas/quict-ml
Author: Library for Quantum Computation and Theoretical Computer Science, ICT, CAS
Author-email: quact@ict.ac.cn
License: Apache License 2.0
Platform: Windows
Platform: Linux
Platform: macOS
Requires-Python: >=3.8
Requires-Dist: QuICT (>=1.0.0)
